MANIFEST.in
README.rst
requirements.txt
setup.cfg
setup.py
versioneer.py
./.travis.yml
./readthedocs.yml
./docs/environment.yml
./docs/build/html/api.html
./docs/build/html/genindex.html
./docs/build/html/index.html
./docs/build/html/quickstart.html
./docs/build/html/search.html
./docs/build/html/_modules/index.html
./docs/build/html/_modules/intake_elasticsearch.html
./docs/build/html/_modules/intake_elasticsearch/elasticsearch_seq.html
./docs/build/html/_modules/intake_elasticsearch/elasticsearch_table.html
./tests/sample1.csv
docs/source/api.rst
docs/source/conf.py
docs/source/index.rst
docs/source/quickstart.rst
intake_elasticsearch/__init__.py
intake_elasticsearch/_version.py
intake_elasticsearch/elasticsearch_seq.py
intake_elasticsearch/elasticsearch_table.py
intake_elasticsearch.egg-info/PKG-INFO
intake_elasticsearch.egg-info/SOURCES.txt
intake_elasticsearch.egg-info/dependency_links.txt
intake_elasticsearch.egg-info/not-zip-safe
intake_elasticsearch.egg-info/pbr.json
intake_elasticsearch.egg-info/requires.txt
intake_elasticsearch.egg-info/top_level.txt
tests/__init__.py
tests/test_intake_es.py
tests/util.py